swift/__init__.py
swift/storage.py
swift/utils.py
django_storage_swift-1.4.0.dist-info/LICENSE.txt
django_storage_swift-1.4.0.dist-info/METADATA
django_storage_swift-1.4.0.dist-info/WHEEL
django_storage_swift-1.4.0.dist-info/top_level.txt
django_storage_swift-1.4.0.dist-info/RECORD
