Metadata-Version: 2.1
Name: django-storage-swift
Version: 1.4.0
Summary: OpenStack Swift storage backend for Django
Home-page: https://github.com/dennisv/django-storage-swift
Author: Dennis Vermeulen
Author-email: blacktorn@gmail.com
License: MIT
Classifier: Environment :: Web Environment
Classifier: Framework :: Django
Classifier: Intended Audience :: Developers
Classifier: License :: OSI Approved :: MIT License
Classifier: Programming Language :: Python
Classifier: Programming Language :: Python :: 3
Classifier: Programming Language :: Python :: 3.8
Classifier: Topic :: Internet :: WWW/HTTP :: Dynamic Content
Classifier: Topic :: Software Development
Classifier: Topic :: Software Development :: Libraries :: Application Frameworks
License-File: LICENSE.txt
Requires-Dist: python-swiftclient >=2.2.0
Requires-Dist: python-keystoneclient >=0.2.3
Requires-Dist: six
Requires-Dist: python-magic >=0.4.10
